blacken_docs/__init__.py
blacken_docs/__main__.py
blacken_docs/py.typed
blacken_docs-1.19.1.dist-info/LICENSE
blacken_docs-1.19.1.dist-info/METADATA
blacken_docs-1.19.1.dist-info/WHEEL
blacken_docs-1.19.1.dist-info/entry_points.txt
blacken_docs-1.19.1.dist-info/top_level.txt
blacken_docs-1.19.1.dist-info/RECORD
