Metadata-Version: 2.1
Name: blacken-docs
Version: 1.19.1
Summary: Run Black on Python code blocks in documentation files.
Author-email: Anthony Sottile <asottile@umich.edu>
Maintainer-email: Adam Johnson <me@adamj.eu>
Project-URL: Changelog, https://github.com/adamchainz/blacken-docs/blob/main/CHANGELOG.rst
Project-URL: Repository, https://github.com/asottile/blacken-docs
Classifier: Development Status :: 5 - Production/Stable
Classifier: Intended Audience :: Developers
Classifier: License :: OSI Approved :: MIT License
Classifier: Natural Language :: English
Classifier: Operating System :: OS Independent
Classifier: Programming Language :: Python :: 3 :: Only
Classifier: Programming Language :: Python :: 3.9
Classifier: Programming Language :: Python :: 3.10
Classifier: Programming Language :: Python :: 3.11
Classifier: Programming Language :: Python :: 3.12
Classifier: Programming Language :: Python :: 3.13
Classifier: Typing :: Typed
Requires-Python: >=3.9
License-File: LICENSE
Requires-Dist: black>=22.1
